{
  "kind": "collectionType",
  "collectionName": "orders",
  "info": {
    "name": "Order"
  },
  "options": {
    "increments": true,
    "timestamps": true,
    "draftAndPublish": true
  },
  "attributes": {
    "Order_number": {
      "type": "uid"
    },
    "username": {
      "type": "string"
    },
    "email": {
      "type": "email"
    },
    "products": {
      "type": "json"
    },
    "telephone": {
      "type": "biginteger"
    },
    "address": {
      "type": "string"
    },
    "country": {
      "type": "string"
    },
    "date": {
      "type": "datetime"
    },
    "status": {
      "type": "string"
    },
    "total": {
      "type": "decimal"
    },
    "pagamento": {
      "type": "string"
    },
    "delivery": {
      "type": "string"
    }
  }
}
